{
  "type": "redirect",
  "data": {
    "location": "http://my.own.domain.tld/pis-control-center/data/the-real-pis-data.json"
  },
  "ttl": 3600, // time to live <https://en.wikipedia.org/wiki/Time_to_live> #g
  "origin": "http://example.org/redirect.pis.json", // on backup/fallback files to show the origin source
  "secure": {
    "hash": { // to check for changes
      "md5": "344aab9758bb0d018b93739e7893fb3a",
      "crc32": "215568175"
    },
    "ca": "http://example.org/pgp.asc", // Certificate authority
    "signature": "" // GPG Signature
  }
}
